{
    "cards": [
        6044,
        6766,
        10213
    ],
    "notes": {},
    "qaData": {
        "en": {
            "answer": "The Special Summon performed by Miracle Contact's effect is not treated as a Fusion Summon. Thus, the effect of King of the Swamp or similar cards cannot be applied.",
            "id": 12371,
            "question": "Is it possible to use King of the Swamp, or a similar monster, as a substitute for one of the Fusion Material monsters when Special Summoning Elemental HERO Aqua Neos with Miracle Contact?",
            "thisSrc": {
                "date": "2021-03-01",
                "misc": "gallantron",
                "type": 4
            },
            "title": "Can King of the Swamp be used with Miracle Contact?",
            "tlSrc": {
                "date": "2017-03-24",
                "type": 0
            },
            "translationStatus": "confirmed"
        },
        "ja": {
            "answer": "\u300c<<10213>>\u300d\u306e\u52b9\u679c\u306b\u3088\u308b\u7279\u6b8a\u53ec\u559a\u306f\u878d\u5408\u53ec\u559a\u3068\u3057\u3066\u6271\u308f\u308c\u306a\u3044\u70ba\u3001\u300c<<6044>>\u300d\u7b49\u306e\u300e\u3053\u306e\u30ab\u30fc\u30c9\u3092\u878d\u5408\u7d20\u6750\u30e2\u30f3\u30b9\u30bf\u30fc\uff11\u4f53\u306e\u4ee3\u308f\u308a\u306b\u3059\u308b\u4e8b\u304c\u3067\u304d\u308b\u300f\u52b9\u679c\u3092\u9069\u7528\u3059\u308b\u4e8b\u306f\u3067\u304d\u307e\u305b\u3093\u3002",
            "id": 12371,
            "question": "\u300c<<10213>>\u300d\u306b\u3088\u3063\u3066\u300c<<6766>>\u300d\u7b49\u3092\u7279\u6b8a\u53ec\u559a\u3059\u308b\u969b\u306b\u3001\u300c<<6044>>\u300d\u7b49\u3092\u878d\u5408\u7d20\u6750\u30e2\u30f3\u30b9\u30bf\u30fc1\u4f53\u306e\u4ee3\u308f\u308a\u3068\u3057\u3066\u4f7f\u7528\u3059\u308b\u4e8b\u306f\u3067\u304d\u307e\u3059\u304b\uff1f",
            "thisSrc": {
                "date": "2017-03-24",
                "type": 0
            },
            "title": "\u300c<<10213>>\u300d\u306e\u52b9\u679c\u306b\u3088\u3063\u3066\u300c<<6766>>\u300d\u7b49\u3092\u7279\u6b8a\u53ec\u559a\u3059\u308b\u969b\u306b\u3001\u300c<<6044>>\u300d\u7b49\u3092\u4f7f\u7528\u3067\u304d\u307e\u3059\u304b\uff1f"
        }
    },
    "tags": [
        "k:Fusion"
    ]
}