{
    "cards": [
        5505,
        5560,
        10819
    ],
    "notes": {
        "precedent": [
            {
                "body": "Possession of temporarily banished cards",
                "date": "2021-05-14",
                "idx": 0,
                "localeMask": 255,
                "owner": "gallantron"
            }
        ]
    },
    "qaData": {
        "en": {
            "answer": "As in the given situation, the monster banished by Interdimensional Matter Transporter is an opponent's banished card, so it counts towards the number of opponent's banished cards. Thus, the ATK of your Angel of Zera will be increased by 100.",
            "id": 13724,
            "question": "I banish a monster originally owned by my opponent that I took control of with Enemy Controller using my Interdimensional Matter Transporter.\n\nIn this case, will the ATK of my Angel of Zera be increased by 100?",
            "thisSrc": {
                "date": "2020-09-30",
                "misc": "pazim",
                "type": 4
            },
            "title": "If I banish an opponent's monster I gained control of with Interdimensional Matter Transporter, will the ATK of my Angel of Zera increase?",
            "tlSrc": {
                "date": "2017-03-24",
                "type": 0
            },
            "translationStatus": "confirmed"
        },
        "ja": {
            "answer": "\u8cea\u554f\u306e\u72b6\u6cc1\u306e\u5834\u5408\u3001\u300c<<5560>>\u300d\u306e\u52b9\u679c\u306b\u3088\u3063\u3066\u9664\u5916\u3055\u308c\u305f\u30e2\u30f3\u30b9\u30bf\u30fc\u306f\u3001\u300c<<10819>>\u300d\u3092\u30b3\u30f3\u30c8\u30ed\u30fc\u30eb\u3057\u3066\u3044\u308b\u81ea\u5206\u304b\u3089\u898b\u3066\u3001\u76f8\u624b\u306e\u30ab\u30fc\u30c9\u3068\u306a\u308a\u307e\u3059\u306e\u3067\u3001\u305d\u306e\u9664\u5916\u3055\u308c\u305f\u30ab\u30fc\u30c9\u306e\u5206\u3082\u542b\u3081\u3066\u3001\u300e\u2460\uff1a\u3053\u306e\u30ab\u30fc\u30c9\u306e\u653b\u6483\u529b\u306f\u9664\u5916\u3055\u308c\u3066\u3044\u308b\u76f8\u624b\u306e\u30ab\u30fc\u30c9\u306e\u6570\u00d7\uff11\uff10\uff10\u30a2\u30c3\u30d7\u3059\u308b\u300f\u52b9\u679c\u304c\u9069\u7528\u3055\u308c\u308b\u4e8b\u306b\u306a\u308a\u307e\u3059\u3002",
            "id": 13724,
            "question": "\u300c<<5505>>\u300d\u306e\u52b9\u679c\u306b\u3088\u3063\u3066\u30b3\u30f3\u30c8\u30ed\u30fc\u30eb\u3092\u5f97\u3066\u3044\u308b\u5143\u3005\u306e\u6301\u3061\u4e3b\u304c\u76f8\u624b\u306e\u30e2\u30f3\u30b9\u30bf\u30fc\u3092\u300c<<5560>>\u300d\u306e\u52b9\u679c\u3067\u9664\u5916\u3057\u307e\u3057\u305f\u3002\n\n\u3053\u306e\u5834\u5408\u3001\u300e\u2460\uff1a\u3053\u306e\u30ab\u30fc\u30c9\u306e\u653b\u6483\u529b\u306f\u9664\u5916\u3055\u308c\u3066\u3044\u308b\u76f8\u624b\u306e\u30ab\u30fc\u30c9\u306e\u6570\u00d7\uff11\uff10\uff10\u30a2\u30c3\u30d7\u3059\u308b\u300f\u52b9\u679c\u306b\u3088\u3063\u3066\u3001\u81ea\u5206\u30d5\u30a3\u30fc\u30eb\u30c9\u306e\u300c<<10819>>\u300d\u306e\u653b\u6483\u529b\u306f\u30a2\u30c3\u30d7\u3057\u307e\u3059\u304b\uff1f",
            "thisSrc": {
                "date": "2017-03-24",
                "type": 0
            },
            "title": "\u300c<<5560>>\u300d\u306e\u52b9\u679c\u3067\u3001\u5143\u3005\u306e\u6301\u3061\u4e3b\u304c\u76f8\u624b\u306e\u30e2\u30f3\u30b9\u30bf\u30fc\u3092\u9664\u5916\u3057\u305f\u5834\u5408\u3001\u300c<<10819>>\u300d\u306e\u653b\u6483\u529b\u306f\u30a2\u30c3\u30d7\u3057\u307e\u3059\u304b\uff1f"
        }
    },
    "tags": [
        "k:Xyz",
        "o:Important Precedent"
    ]
}