{
    "cards": [
        4956,
        5914,
        11914
    ],
    "notes": {},
    "qaData": {
        "en": {
            "answer": "If Ceasefire or Compulsory Evacuation Device are chained to Black Cat-astrophe, and you have 1 or less Set monsters on your side of the field when it resolves, the effect that ends the Battle Phase is applied normally.",
            "id": 15984,
            "question": "If Black Cat-astrophe is activated, but Ceasefire or Compulsory Evacuation Device are chained so that the number of Set monsters on my side of the field is 1 or less when it resolves, is the effect still applied?",
            "thisSrc": {
                "date": "2015-05-18",
                "misc": "???",
                "type": 4
            },
            "title": "If Black Cat-astrophe is activated, but Ceasefire or Compulsory Evacuation Device are chained so that the number of Set monsters on my side of the field is 1 or less when it resolves, is the effect still applied?",
            "tlSrc": {
                "date": "2017-03-24",
                "type": 0
            },
            "translationStatus": "unconfirmable"
        },
        "ja": {
            "answer": "\u300c<<11914>>\u300d\u306e\u30ab\u30fc\u30c9\u306e\u767a\u52d5\u306b\u30c1\u30a7\u30fc\u30f3\u3057\u305f\u300c<<5914>>\u300d\u3084\u300c<<4956>>\u300d\u306e\u52b9\u679c\u306b\u3088\u3063\u3066\u3001\u52b9\u679c\u51e6\u7406\u6642\u306b\u3001\u81ea\u5206\u306e\u30e2\u30f3\u30b9\u30bf\u30fc\u30be\u30fc\u30f3\u306b\u88cf\u5074\u5b88\u5099\u8868\u793a\u30e2\u30f3\u30b9\u30bf\u30fc\u304c1\u4f53\u4ee5\u4e0b\u306b\u306a\u3063\u305f\u5834\u5408\u3067\u3082\u3001\u300e\u305d\u306e\u30d0\u30c8\u30eb\u30d5\u30a7\u30a4\u30ba\u3092\u7d42\u4e86\u3059\u308b\u300f\u51e6\u7406\u306f\u901a\u5e38\u901a\u308a\u9069\u7528\u3055\u308c\u307e\u3059\u3002",
            "id": 15984,
            "question": "\u300c<<11914>>\u300d\u306e\u300e\u2460\uff1a\u81ea\u5206\u30d5\u30a3\u30fc\u30eb\u30c9\u306b\u88cf\u5074\u5b88\u5099\u8868\u793a\u30e2\u30f3\u30b9\u30bf\u30fc\u304c\uff12\u4f53\u4ee5\u4e0a\u5b58\u5728\u3059\u308b\u5834\u5408\u3001\u76f8\u624b\u30d0\u30c8\u30eb\u30d5\u30a7\u30a4\u30ba\u306b\u767a\u52d5\u3067\u304d\u308b\u3002\u305d\u306e\u30d0\u30c8\u30eb\u30d5\u30a7\u30a4\u30ba\u3092\u7d42\u4e86\u3059\u308b\u300f\u52b9\u679c\u306e\u767a\u52d5\u306b\u30c1\u30a7\u30fc\u30f3\u3057\u3066\u3001\u76f8\u624b\u304c\u300c<<5914>>\u300d\u3084\u300c<<4956>>\u300d\u3092\u767a\u52d5\u3057\u3001\u81ea\u5206\u306e\u30e2\u30f3\u30b9\u30bf\u30fc\u30be\u30fc\u30f3\u306b\u88cf\u5074\u5b88\u5099\u8868\u793a\u30e2\u30f3\u30b9\u30bf\u30fc\u304c1\u4f53\u4ee5\u4e0b\u306b\u306a\u3063\u305f\u5834\u5408\u3001\u300c<<11914>>\u300d\u306e\u52b9\u679c\u51e6\u7406\u306f\u3069\u3046\u306a\u308a\u307e\u3059\u304b\uff1f",
            "thisSrc": {
                "date": "2017-03-24",
                "type": 0
            },
            "title": "\u300c<<11914>>\u300d\u306e\u30ab\u30fc\u30c9\u306e\u767a\u52d5\u306b\u30c1\u30a7\u30fc\u30f3\u3057\u3066\u3001\u81ea\u5206\u30d5\u30a3\u30fc\u30eb\u30c9\u306b\u88cf\u5074\u5b88\u5099\u8868\u793a\u30e2\u30f3\u30b9\u30bf\u30fc\u304c1\u4f53\u4ee5\u4e0b\u306b\u306a\u3063\u305f\u5834\u5408\u3001\u51e6\u7406\u306f\u3069\u3046\u306a\u308a\u307e\u3059\u304b\uff1f"
        }
    },
    "tags": [
        "k:Chain"
    ]
}