{
    "cards": [
        5505,
        13080,
        13109
    ],
    "notes": {},
    "qaData": {
        "en": {
            "answer": "When resolving the effect of Supreme Rage that activates in the Graveyard, if Supreme King Dragon Dark Rebellion is on your opponent's side of the field, \"Supreme King Dragon\" monsters are attached to it from your Extra Deck and/or Graveyard normally.",
            "id": 20828,
            "question": "I activate the second effect of Supreme Rage, targeting a face-up Supreme King Dragon Dark Rebellion on my field. If my opponent chains Enemy Controller and takes control of Supreme King Dragon Dark Rebellion, how does the effect of Supreme Rage resolve?",
            "thisSrc": {
                "date": "2017-08-05",
                "misc": "???",
                "type": 4
            },
            "title": "I activate the second effect of Supreme Rage, targeting a face-up Supreme King Dragon Dark Rebellion on my field. If my opponent chains Enemy Controller and takes control of Supreme King Dragon Dark Rebellion, how does the effect of Supreme Rage resolve?",
            "tlSrc": {
                "date": "2017-07-28",
                "type": 0
            },
            "translationStatus": "unconfirmable"
        },
        "ja": {
            "answer": "\u5893\u5730\u306b\u3066\u767a\u52d5\u3059\u308b\u300c<<13109>>\u300d\u306e\u52b9\u679c\u51e6\u7406\u6642\u306b\u3001\u5bfe\u8c61\u306e\u300c<<13080>>\u300d\u306e\u30b3\u30f3\u30c8\u30ed\u30fc\u30eb\u304c\u76f8\u624b\u306b\u79fb\u3063\u3066\u3044\u308b\u5834\u5408\u3067\u3082\u3001\u300e\u81ea\u5206\u306e\u5893\u5730\u306e\u30e2\u30f3\u30b9\u30bf\u30fc\u53ca\u3073\u81ea\u5206\u306eEX\u30c7\u30c3\u30ad\u306e\u8868\u5074\u8868\u793a\u306eP\u30e2\u30f3\u30b9\u30bf\u30fc\u306e\u4e2d\u304b\u3089\u3001\u300c\u8987\u738b\u7737\u7adc\u300d\u30e2\u30f3\u30b9\u30bf\u30fc\uff12\u4f53\u3092\u9078\u3073\u3001\u5bfe\u8c61\u306e\u30e2\u30f3\u30b9\u30bf\u30fc\u306e\u4e0b\u306b\u91cd\u306d\u3066X\u7d20\u6750\u3068\u3059\u308b\u300f\u51e6\u7406\u306f\u901a\u5e38\u901a\u308a\u9069\u7528\u3055\u308c\u307e\u3059\u3002",
            "id": 20828,
            "question": "\u300c<<13109>>\u300d\u306e\u300e\u2461\uff1a\u5893\u5730\u306e\u3053\u306e\u30ab\u30fc\u30c9\u3092\u9664\u5916\u3057\u3001\u81ea\u5206\u30d5\u30a3\u30fc\u30eb\u30c9\u306e\u300c\u8987\u738b\u7737\u7adc\u300dX\u30e2\u30f3\u30b9\u30bf\u30fc\uff11\u4f53\u3092\u5bfe\u8c61\u3068\u3057\u3066\u767a\u52d5\u3067\u304d\u308b\u3002\u81ea\u5206\u306e\u5893\u5730\u306e\u30e2\u30f3\u30b9\u30bf\u30fc\u53ca\u3073\u81ea\u5206\u306eEX\u30c7\u30c3\u30ad\u306e\u8868\u5074\u8868\u793a\u306eP\u30e2\u30f3\u30b9\u30bf\u30fc\u306e\u4e2d\u304b\u3089\u3001\u300c\u8987\u738b\u7737\u7adc\u300d\u30e2\u30f3\u30b9\u30bf\u30fc\uff12\u4f53\u3092\u9078\u3073\u3001\u5bfe\u8c61\u306e\u30e2\u30f3\u30b9\u30bf\u30fc\u306e\u4e0b\u306b\u91cd\u306d\u3066X\u7d20\u6750\u3068\u3059\u308b\u300f\u52b9\u679c\u3092\u767a\u52d5\u3057\u3001\u81ea\u5206\u306e\u30e2\u30f3\u30b9\u30bf\u30fc\u30be\u30fc\u30f3\u306b\u8868\u5074\u8868\u793a\u3067\u5b58\u5728\u3059\u308b\u300c<<13080>>\u300d\u3092\u5bfe\u8c61\u3068\u3057\u307e\u3057\u305f\u3002\n\n\u305d\u306e\u52b9\u679c\u306e\u767a\u52d5\u306b\u30c1\u30a7\u30fc\u30f3\u3057\u3066\u300c<<5505>>\u300d\u306e\u300e\u25cf\u81ea\u5206\u30d5\u30a3\u30fc\u30eb\u30c9\u306e\u30e2\u30f3\u30b9\u30bf\u30fc\uff11\u4f53\u3092\u30ea\u30ea\u30fc\u30b9\u3057\u3001\u76f8\u624b\u30d5\u30a3\u30fc\u30eb\u30c9\u306e\u8868\u5074\u8868\u793a\u30e2\u30f3\u30b9\u30bf\u30fc\uff11\u4f53\u3092\u5bfe\u8c61\u3068\u3057\u3066\u767a\u52d5\u3067\u304d\u308b\u3002\u305d\u306e\u8868\u5074\u8868\u793a\u30e2\u30f3\u30b9\u30bf\u30fc\u306e\u30b3\u30f3\u30c8\u30ed\u30fc\u30eb\u3092\u30a8\u30f3\u30c9\u30d5\u30a7\u30a4\u30ba\u307e\u3067\u5f97\u308b\u300f\u52b9\u679c\u304c\u767a\u52d5\u3057\u3001\u5bfe\u8c61\u306e\u300c<<13080>>\u300d\u306e\u30b3\u30f3\u30c8\u30ed\u30fc\u30eb\u304c\u76f8\u624b\u306b\u79fb\u3063\u3066\u3044\u308b\u5834\u5408\u3001\u52b9\u679c\u51e6\u7406\u306f\u3069\u3046\u306a\u308a\u307e\u3059\u304b\uff1f",
            "thisSrc": {
                "date": "2017-07-28",
                "type": 0
            },
            "title": "\u5893\u5730\u306b\u3066\u767a\u52d5\u3059\u308b\u300c<<13109>>\u300d\u306e\u52b9\u679c\u51e6\u7406\u6642\u306b\u3001\u5bfe\u8c61\u306e\u300c<<13080>>\u300d\u306e\u30b3\u30f3\u30c8\u30ed\u30fc\u30eb\u304c\u76f8\u624b\u306b\u79fb\u3063\u3066\u3044\u308b\u5834\u5408\u3001\u51e6\u7406\u306f\u3069\u3046\u306a\u308a\u307e\u3059\u304b\uff1f"
        }
    },
    "tags": [
        "k:Trap"
    ]
}